{
  "first_name": {
    "jahn": {
      "reference_count": 1,
      "word_length": 4,
      "variants": {
        "john": {
          "frequency": 1,
          "length_variant": 4,
          "edit_distance": 1,
          "low_similarity": true,
          "mismatch_first4": true
        },
        "jon": {
          "frequency": 1,
          "length_variant": 3,
          "edit_distance": 2,
          "low_similarity": true,
          "mismatch_first4": true
        }
      }
    },
    "johnny": {
      "reference_count": 1,
      "word_length": 6,
      "variants": {
        "jhon": {
          "frequency": 1,
          "length_variant": 4,
          "edit_distance": 3,
          "low_similarity": true,
          "mismatch_first4": true
        },
        "johm": {
          "frequency": 1,
          "length_variant": 4,
          "edit_distance": 3,
          "low_similarity": true,
          "mismatch_first4": true
        }
      }
    }
  },
  "last_name": {
    "smyth": {
      "reference_count": 1,
      "word_length": 5,
      "variants": {
        "smith": {
          "frequency": 1,
          "length_variant": 5,
          "edit_distance": 1,
          "low_similarity": false,
          "mismatch_first4": true
        },
        "smoth": {
          "frequency": 1,
          "length_variant": 5,
          "edit_distance": 1,
          "low_similarity": false,
          "mismatch_first4": true
        }
      }
    },
    "smith": {
      "reference_count": 1,
      "word_length": 5,
      "variants": {
        "smih": {
          "frequency": 1,
          "length_variant": 4,
          "edit_distance": 1,
          "low_similarity": false,
          "mismatch_first4": true
        },
        "smiht": {
          "frequency": 1,
          "length_variant": 5,
          "edit_distance": 2,
          "low_similarity": false,
          "mismatch_first4": true
        }
      }
    }
  },
  "sex": {
    "m": {
      "reference_count": 2,
      "word_length": 1,
      "variants": {
        "male": {
          "frequency": 1,
          "length_variant": 4
        }
      }
    },
    "female": {
      "reference_count": 1,
      "word_length": 6,
      "variants": {
        "f": {
          "frequency": 2,
          "length_variant": 1
        }
      }
    }
  },
  "dob": {
    "1985/06/15": {
      "reference_count": 1,
      "word_length": 10,
      "variants": {
        "1985-06-15": {
          "frequency": 1,
          "length_variant": 10,
          "exploded": false
        },
        "15-06-1985": {
          "frequency": 1,
          "length_variant": 10,
          "exploded": false
        }
      }
    },
    "19850615": {
      "reference_count": 1,
      "word_length": 8,
      "variants": {
        "1985-06-16": {
          "frequency": 1,
          "length_variant": 10,
          "exploded": true
        },
        "1985-6-15": {
          "frequency": 1,
          "length_variant": 9,
          "exploded": false
        }
      }
    }
  },
  "address": {
    "124 main st": {
      "reference_count": 1,
      "word_length": 11,
      "variants": {
        "123 main st": {
          "frequency": 1,
          "length_variant": 11
        },
        "123 main street": {
          "frequency": 1,
          "length_variant": 15
        }
      }
    },
    "123 main st, apt 1": {
      "reference_count": 1,
      "word_length": 18,
      "variants": {
        "123 main st.": {
          "frequency": 1,
          "length_variant": 12
        },
        "123 main st apt1": {
          "frequency": 1,
          "length_variant": 16
        }
      }
    }
  },
  "postcode": {
    "sw1a1a": {
      "reference_count": 1,
      "word_length": 6,
      "variants": {
        "sw1a1aa": {
          "frequency": 1,
          "length_variant": 7,
          "edit_distance": 1
        },
        "sw1a 1aa": {
          "frequency": 1,
          "length_variant": 8,
          "edit_distance": 2
        }
      }
    },
    "sw1a1aa": {
      "reference_count": 1,
      "word_length": 7,
      "variants": {
        "sw1a1ab": {
          "frequency": 1,
          "length_variant": 7,
          "edit_distance": 1
        },
        "sw1a1ba": {
          "frequency": 1,
          "length_variant": 7,
          "edit_distance": 1
        }
      }
    }
  },
  "telephone": {
    "0207946000": {
      "reference_count": 1,
      "word_length": 10,
      "variants": {
        "2079460000": {
          "frequency": 1,
          "length_variant": 10
        },
        "+44 20 79460000": {
          "frequency": 1,
          "length_variant": 15
        }
      }
    }
  },
  "email": {
    "johnsmith@example.com": {
      "reference_count": 1,
      "word_length": 21,
      "variants": {
        "john.smith@exmaple.com": {
          "frequency": 1,
          "length_variant": 22
        },
        "john.smith@example.co.uk": {
          "frequency": 1,
          "length_variant": 24
        }
      }
    },
    "john.smith@example.com": {
      "reference_count": 1,
      "word_length": 22,
      "variants": {
        "john.smit@example.com": {
          "frequency": 1,
          "length_variant": 21
        },
        "john.smith@example.org": {
          "frequency": 1,
          "length_variant": 22
        }
      }
    }
  }
}
